flowws/Argument.py
flowws/DirectoryStorage.py
flowws/GetarStorage.py
flowws/PatternMatcher.py
flowws/Stage.py
flowws/Storage.py
flowws/Workflow.py
flowws/__init__.py
flowws/freeze.py
flowws/internal.py
flowws/run.py
flowws/version.py
flowws-0.6.0.dist-info/LICENSE
flowws-0.6.0.dist-info/METADATA
flowws-0.6.0.dist-info/WHEEL
flowws-0.6.0.dist-info/entry_points.txt
flowws-0.6.0.dist-info/top_level.txt
flowws-0.6.0.dist-info/RECORD
