Metadata-Version: 2.1
Name: flowws
Version: 0.6.0
Summary: Library for development of stage-based scientific workflows
Author: Matthew Spellings
Author-email: matthew.p.spellings@gmail.com
License: MIT
Classifier: Development Status :: 3 - Alpha
Classifier: License :: OSI Approved :: MIT License
Classifier: Programming Language :: Python :: 3
Requires-Python: >=3
License-File: LICENSE
